line_items/__init__.py
line_items/line_items.cpython-314-x86_64-linux-gnu.so
line_items-0.1.6.dist-info/METADATA
line_items-0.1.6.dist-info/WHEEL
line_items-0.1.6.dist-info/RECORD
line_items-0.1.6.dist-info/licenses/LICENSE
