Metadata-Version: 2.4
Name: line_items
Version: 0.1.6
Classifier: Programming Language :: Rust
Classifier: Programming Language :: Python :: Implementation :: CPython
License-File: LICENSE
Summary: A set of line item calculation utilities for Artconomy.com.
Author: Fox Danger Piacenti <fox@artconomy.com>
Author-email: Fox Danger Piacenti <fox@artconomy.com>
License: AGPL-3
Requires-Python: >=3.14
Project-URL: Source Code, https://gitlab.com/artconomy/line_items
